README.md
setup.py
pyatn_client/__init__.py
pyatn_client/atn.py
pyatn_client/contracts.json
pyatn_client/log.py
pyatn_client/pyatn.py
pyatn_client/utils.py
pyatn_client.egg-info/PKG-INFO
pyatn_client.egg-info/SOURCES.txt
pyatn_client.egg-info/dependency_links.txt
pyatn_client.egg-info/entry_points.txt
pyatn_client.egg-info/requires.txt
pyatn_client.egg-info/top_level.txt
pyatn_client/microraiden/__init__.py
pyatn_client/microraiden/config.py
pyatn_client/microraiden/constants.py
pyatn_client/microraiden/contracts.json
pyatn_client/microraiden/exceptions.py
pyatn_client/microraiden/header.py
pyatn_client/microraiden/client/__init__.py
pyatn_client/microraiden/client/channel.py
pyatn_client/microraiden/client/client.py
pyatn_client/microraiden/client/context.py
pyatn_client/microraiden/utils/__init__.py
pyatn_client/microraiden/utils/contract.py
pyatn_client/microraiden/utils/crypto.py
pyatn_client/microraiden/utils/misc.py
pyatn_client/microraiden/utils/populus_compat.py
pyatn_client/microraiden/utils/private_key.py
test/test.py
test/test_atn.py
test/test_call.py
test/test_channel.py