Metadata-Version: 2.1
Name: pyatn-client
Version: 0.1.0
Summary: Python ATN Client
Home-page: https://github.com/ATNIO/pyatn-client
Author: ovsoil
Author-email: huaxin.yu@atmatrix.org
License: UNKNOWN
Platform: UNKNOWN
Classifier: Programming Language :: Python :: 3
Classifier: License :: OSI Approved :: MIT License
Classifier: Operating System :: OS Independent
